{"version": "https://jsonfeed.org/version/1", "title": "PhilFan's Notebook", "home_page_url": "https://www.philfan.cn/", "feed_url": "https://www.philfan.cn/feed_json_created.json", "description": "PhilFan\u7684\u7b14\u8bb0\u672c", "icon": null, "authors": [{"name": "PhilFan"}], "language": "zh", "items": [{"id": "https://www.philfan.cn/blog/2025/08/07/%E5%85%89%E9%94%A5%E4%BB%A5%E5%86%85%E7%9A%86%E6%98%AF%E5%91%BD%E8%BF%90.html", "url": "https://www.philfan.cn/blog/2025/08/07/%E5%85%89%E9%94%A5%E4%BB%A5%E5%86%85%E7%9A%86%E6%98%AF%E5%91%BD%E8%BF%90.html", "title": "\u5149\u9525\u4ee5\u5185\u7686\u662f\u547d\u8fd0", "content_html": "<h1>\u5149\u9525\u4ee5\u5185\u7686\u662f\u547d\u8fd0</h1>\n<p>\u65f6\u95f4\u7684\u7ebf\u6027\u662f\u6e29\u67d4\u7684\u9a97\u5c40</p>", "image": null, "date_published": "2025-08-07T00:00:00+00:00", "authors": [{"name": "Phil-Fan"}], "tags": null}, {"id": "https://www.philfan.cn/blog/2025/08/07/hello-world.html", "url": "https://www.philfan.cn/blog/2025/08/07/hello-world.html", "title": "Hello World!", "content_html": "<h1>Hello World!</h1>\n<p>This is my first blog post.</p>", "image": null, "date_published": "2025-08-07T00:00:00+00:00", "authors": [{"name": "Phil-Fan"}], "tags": null}]}